ipfabric_httpx_auth/__init__.py
ipfabric_httpx_auth/authentication.py
ipfabric_httpx_auth/errors.py
ipfabric_httpx_auth/oauth2_tokens.py
ipfabric_httpx_auth-6.0.1.dist-info/LICENSE
ipfabric_httpx_auth-6.0.1.dist-info/METADATA
ipfabric_httpx_auth-6.0.1.dist-info/WHEEL
ipfabric_httpx_auth-6.0.1.dist-info/RECORD
