Metadata-Version: 2.1
Name: ipfabric-httpx-auth
Version: 6.0.1
Summary: DEPRECATED: Authentication plugin for IP Fabric
License: MIT
Keywords: ipfabric,ip-fabric,community-fabric
Author: Justin Jeffery
Author-email: justin.jeffery@ipfabric.io
Requires-Python: >=3.7.1,<4.0.0
Classifier: License :: OSI Approved :: MIT License
Classifier: Programming Language :: Python :: 3
Classifier: Programming Language :: Python :: 3.8
Classifier: Programming Language :: Python :: 3.9
Classifier: Programming Language :: Python :: 3.10
Classifier: Programming Language :: Python :: 3.11
Requires-Dist: PyJWT (>=2.4.0,<3.0.0)
Requires-Dist: httpx (>=0.23.0,<0.24.0)
Project-URL: IP Fabric, https://ipfabric.io/
